odoo/addons/bi_sql_editor_aggregate/README.rst
odoo/addons/bi_sql_editor_aggregate/__init__.py
odoo/addons/bi_sql_editor_aggregate/__manifest__.py
odoo/addons/bi_sql_editor_aggregate/description/icon.png
odoo/addons/bi_sql_editor_aggregate/i18n/bi_sql_editor_aggregate.pot
odoo/addons/bi_sql_editor_aggregate/models/__init__.py
odoo/addons/bi_sql_editor_aggregate/models/bi_sql_view.py
odoo/addons/bi_sql_editor_aggregate/models/bi_sql_view_field.py
odoo/addons/bi_sql_editor_aggregate/models/ir_model.py
odoo/addons/bi_sql_editor_aggregate/static/description/icon.png
odoo/addons/bi_sql_editor_aggregate/views/view_bi_sql_view.xml
odoo12_addon_bi_sql_editor_aggregate-12.0.1.1.0.dist-info/METADATA
odoo12_addon_bi_sql_editor_aggregate-12.0.1.1.0.dist-info/WHEEL
odoo12_addon_bi_sql_editor_aggregate-12.0.1.1.0.dist-info/top_level.txt
odoo12_addon_bi_sql_editor_aggregate-12.0.1.1.0.dist-info/RECORD
